vegav1/__init__.py
vegav1/x.py
vegav1-0.1.data/scripts/ryb
vegav1-0.1.dist-info/LICENSE
vegav1-0.1.dist-info/METADATA
vegav1-0.1.dist-info/WHEEL
vegav1-0.1.dist-info/top_level.txt
vegav1-0.1.dist-info/RECORD
